{
  "data": {
    "breakBlockSound": {
      "volume": {
        "value": 0
      }
    },
    "collisionBoxes": [
      {
        "max": {
          "y": 0.5
        }
      },
      {
        "min": {
          "x": 0.5,
          "y": 0.5
        }
      }
    ],
    "dropSelf": {
      "canDropSelf": false
    },
    "isOpaqueFullCube": false,
    "isQuad": true,
    "name": {
      "value": "block_sandstone_stairs01"
    },
    "placeBlockSound": {
      "volume": {
        "value": 0
      }
    }
  },
  "meta": {
    "EXPORT": {
      "setting.json": "3f68c9ca36e6a47b797f0b317b921b64",
      "triggers.bts": ""
    },
    "VERSION": "0.22"
  }
}