{
  "data": {
    "breakBlockSound": {
      "volume": {
        "value": 0
      }
    },
    "dropSelf": {
      "canDropSelf": false
    },
    "name": {
      "value": "block_wool_9"
    },
    "placeBlockSound": {
      "volume": {
        "value": 0
      }
    },
    "textures": {
      "back": {
        "asset": "asset/Texture/Block/wool_colored_cyan_wool_9.png"
      },
      "down": {
        "asset": "asset/Texture/Block/wool_colored_cyan_wool_9.png"
      },
      "front": {
        "asset": "asset/Texture/Block/wool_colored_cyan_wool_9.png"
      },
      "left": {
        "asset": "asset/Texture/Block/wool_colored_cyan_wool_9.png"
      },
      "right": {
        "asset": "asset/Texture/Block/wool_colored_cyan_wool_9.png"
      },
      "up": {
        "asset": "asset/Texture/Block/wool_colored_cyan_wool_9.png"
      }
    }
  },
  "meta": {
    "EXPORT": {
      "setting.json": "cbe7d756ec38fb1bf8d774d4c31eb76b",
      "triggers.bts": ""
    },
    "VERSION": "0.22"
  }
}